{
    "$schema": "http://json-schema.org/schema#",
    "type": "object",
    "properties": {
        "hami": {
            "type": "object",
            "properties": {
                "schedulerName": {
                    "type": "string",
                    "default": "hami-scheduler"
                },
                "devicePlugin": {
                    "type": "object",
                    "properties": {
                        "deviceCoreScaling": {
                            "type": "number"
                        },
                        "deviceMemoryScaling": {
                            "type": "number"
                        },
                        "deviceSplitCount": {
                            "type": "integer"
                        }
                    }
                },
                "scheduler": {
                    "type": "object",
                    "properties": {
                        "serviceMonitor": {
                            "type": "object",
                            "properties": {
                                "enable": {
                                    "type": "boolean",
                                    "description": "Ensure the insight-agent is installed and running to enable this feature; otherwise, the nvidia-vgpu installation may fail."
                                }
                            }
                        }
                    }
                }
            },
            "description": "After installation, the original GPU node remains unchanged. Newly added GPU nodes default to use full GPU. If you need to switch to vGPU, please go to the appropriate node to make the switch."
        }
    }
}
